vbtools/__init__.py
vbtools/vbtools.py
vbtools/scripts/vcfbench.py
vbtools/scripts/vcfcnsus.py
vbtools-0.1.0.data/scripts/vcfbench.py
vbtools-0.1.0.data/scripts/vcfcnsus.py
vbtools-0.1.0.dist-info/LICENSE
vbtools-0.1.0.dist-info/METADATA
vbtools-0.1.0.dist-info/WHEEL
vbtools-0.1.0.dist-info/top_level.txt
vbtools-0.1.0.dist-info/RECORD
